.bumpversion
.editorconfig
AUTHORS.rst
CONTRIBUTING.rst
HISTORY.rst
LICENSE
MANIFEST.in
Makefile
Pipfile
README.rst
requirements_dev.txt
setup.cfg
setup.py
tox.ini
.github/ISSUE_TEMPLATE.md
docs/Makefile
docs/authors.rst
docs/conf.py
docs/contributing.rst
docs/history.rst
docs/index.rst
docs/jsoner.rst
docs/make.bat
docs/modules.rst
docs/readme.rst
docs/spelling_wordlist.txt
docs/_build/_sources/authors.rst.txt
docs/_build/_sources/contributing.rst.txt
docs/_build/_sources/history.rst.txt
docs/_build/_sources/index.rst.txt
docs/_build/_sources/installation.rst.txt
docs/_build/_sources/jsoner.rst.txt
docs/_build/_sources/modules.rst.txt
docs/_build/_sources/readme.rst.txt
docs/_build/_sources/usage.rst.txt
docs/_build/_static/ajax-loader.gif
docs/_build/_static/comment-bright.png
docs/_build/_static/comment-close.png
docs/_build/_static/comment.png
docs/_build/_static/down-pressed.png
docs/_build/_static/down.png
docs/_build/_static/file.png
docs/_build/_static/minus.png
docs/_build/_static/plus.png
docs/_build/_static/up-pressed.png
docs/_build/_static/up.png
docs/_build/html/_sources/authors.rst.txt
docs/_build/html/_sources/contributing.rst.txt
docs/_build/html/_sources/history.rst.txt
docs/_build/html/_sources/index.rst.txt
docs/_build/html/_sources/installation.rst.txt
docs/_build/html/_sources/jsoner.rst.txt
docs/_build/html/_sources/jsoner.tests.rst.txt
docs/_build/html/_sources/modules.rst.txt
docs/_build/html/_sources/readme.rst.txt
docs/_build/html/_sources/usage.rst.txt
docs/_build/html/_static/ajax-loader.gif
docs/_build/html/_static/comment-bright.png
docs/_build/html/_static/comment-close.png
docs/_build/html/_static/comment.png
docs/_build/html/_static/down-pressed.png
docs/_build/html/_static/down.png
docs/_build/html/_static/file.png
docs/_build/html/_static/minus.png
docs/_build/html/_static/plus.png
docs/_build/html/_static/up-pressed.png
docs/_build/html/_static/up.png
jsoner/__init__.py
jsoner/errors.py
jsoner/registry.py
jsoner/serialization.py
jsoner.egg-info/PKG-INFO
jsoner.egg-info/SOURCES.txt
jsoner.egg-info/dependency_links.txt
jsoner.egg-info/not-zip-safe
jsoner.egg-info/requires.txt
jsoner.egg-info/top_level.txt
