Metadata-Version: 2.1
Name: jsoner
Version: 0.2.0
Summary: Jsoner allows you to easily convert your classes to json and back.
Home-page: https://github.com/sschaffer92/jsoner
Author: Sebastian Schaffer
License: MIT license
Project-URL: Documentation, https://jsoner.readthedocs.io/en/latest/
Project-URL: Source, https://github.com/sschaffer92/jsoner/
Project-URL: Tracker, https://github.com/sschaffer92/jsoner/issues
Keywords: jsoner json celery django serialization
Platform: UNKNOWN
Classifier: Development Status :: 2 - Pre-Alpha
Classifier: Intended Audience :: Developers
Classifier: License :: OSI Approved :: MIT License
Classifier: Natural Language :: English
Classifier: Programming Language :: Python :: 3
Classifier: Programming Language :: Python :: 3.4
Classifier: Programming Language :: Python :: 3.5
Classifier: Programming Language :: Python :: 3.6
Classifier: Programming Language :: Python :: 3.7
Requires-Python: >=3.4
